LICENSE
README.md
setup.cfg
setup.py
debiai/__init__.py
debiai/config.py
debiai/debiai.py
debiai/debiai_model.py
debiai/debiai_project.py
debiai/debiai_selection.py
debiai/utils.py
debiai.egg-info/PKG-INFO
debiai.egg-info/SOURCES.txt
debiai.egg-info/dependency_links.txt
debiai.egg-info/requires.txt
debiai.egg-info/top_level.txt
debiai/debiai_services/__init__.py
debiai/debiai_services/df_to_dict_tree.py
debiai/debiai_services/np_to_dict.py
tests/__init__.py
tests/test_config.py
tests/test_edge_cases.py
tests/test_get_data.py
tests/test_project_samples.py
tests/test_projects.py
tests/test_url.py