Metadata-Version: 2.1
Name: debiai
Version: 0.30.1
Summary: DebiAI python module
Home-page: https://github.com/debiai/py-debiai
Author: IRT-SystemX
Author-email: debiai@irt-systemx.fr
License: Apache 2.0
Keywords: DebiAI,Data vis,AI,Bias
Classifier: Programming Language :: Python :: 3
Classifier: License :: OSI Approved :: Apache Software License
Classifier: Operating System :: OS Independent
Requires-Python: >=3.6
License-File: LICENSE
Requires-Dist: numpy
Requires-Dist: pandas
Requires-Dist: requests
